event_sink_clickhouse/__init__.py
event_sink_clickhouse/apps.py
event_sink_clickhouse/serializers.py
event_sink_clickhouse/signals.py
event_sink_clickhouse/tasks.py
event_sink_clickhouse/urls.py
event_sink_clickhouse/utils.py
event_sink_clickhouse/waffle.py
event_sink_clickhouse/management/__init__.py
event_sink_clickhouse/management/commands/__init__.py
event_sink_clickhouse/management/commands/dump_data_to_clickhouse.py
event_sink_clickhouse/settings/__init__.py
event_sink_clickhouse/settings/common.py
event_sink_clickhouse/settings/production.py
event_sink_clickhouse/sinks/__init__.py
event_sink_clickhouse/sinks/base_sink.py
event_sink_clickhouse/sinks/course_published.py
event_sink_clickhouse/sinks/external_id_sink.py
event_sink_clickhouse/sinks/user_profile_sink.py
event_sink_clickhouse/sinks/user_retire.py
openedx_event_sink_clickhouse-1.1.1.dist-info/LICENSE.txt
openedx_event_sink_clickhouse-1.1.1.dist-info/METADATA
openedx_event_sink_clickhouse-1.1.1.dist-info/WHEEL
openedx_event_sink_clickhouse-1.1.1.dist-info/entry_points.txt
openedx_event_sink_clickhouse-1.1.1.dist-info/top_level.txt
openedx_event_sink_clickhouse-1.1.1.dist-info/RECORD
